Scripts/__init__.py
Scripts/transparent_earth_EKF.py
Transformations/Transformations.py
Transformations/__init__.py
satellite_sim-0.0.1.dist-info/LICENSE
satellite_sim-0.0.1.dist-info/METADATA
satellite_sim-0.0.1.dist-info/WHEEL
satellite_sim-0.0.1.dist-info/top_level.txt
satellite_sim-0.0.1.dist-info/RECORD
