Metadata-Version: 2.1
Name: satellite-sim
Version: 0.0.1
Summary: Python implementation of satellite simulation for PhD
Home-page: https://github.com/sgboakes/satellite_sim
Author: Benedict Oakes
Author-email: sgboakes@liverpool.ac.uk
License: UNKNOWN
Project-URL: Bug Tracker, https://github.com/sgboakes/satellite_sim/issues
Platform: UNKNOWN
Classifier: Programming Language :: Python :: 3
Classifier: License :: OSI Approved :: MIT License
Classifier: Operating System :: OS Independent
Requires-Python: >=3.6
License-File: LICENSE
